{
  "key": "elemental_synergy",
  "type": "INTERNAL",
  "reactions": [
    {
      "match": ["element_endow:fire", "element_endow:lightning"],
      "rate": 0.15,
      "effect": {
        "afflict": [],
        "empower": [
          ["minecraft:speed", 100, 1, true],
          ["minecraft:strength", 100, 0, true]
        ]
      }
    },
    {
      "match": ["element_endow:water", "element_endow:ice"],
      "rate": 0.12,
      "effect": {
        "afflict": [],
        "empower": [
          ["minecraft:resistance", 100, 1, true],
          ["minecraft:water_breathing", 200, 0, true]
        ]
      }
    },
    {
      "match": ["element_endow:earth", "element_endow:nature"],
      "rate": 0.1,
      "effect": {
        "afflict": [],
        "empower": [
          ["minecraft:regeneration", 100, 0, true],
          ["minecraft:absorption", 100, 0, true]
        ]
      }
    }
  ]
}